dotfigure
