Metadata-Version: 1.1
Name: dotfigure
Version: 0.4
Summary: DOT graph figures for reStructuredText
Home-page: UNKNOWN
Author: Friedrich Freitag
Author-email: frauededed@gmx.net
License: UNKNOWN
Platform: UNKNOWN
Classifier: Development Status :: 3 - Alpha
Classifier: Environment :: Console
Classifier: Environment :: Web Environment
Classifier: Intended Audience :: Developers
Classifier: License :: Public Domain
Classifier: Operating System :: OS Independent
Classifier: Programming Language :: Python
Classifier: Programming Language :: Python :: 2
Classifier: Topic :: Documentation
Classifier: Topic :: Utilities
